discord/ext/colors/__init__.py
discord/ext/colours/__init__.py
discord/ext/colours/crayon.py
discord/ext/colours/xkcd.py
discord_ext_colours-0.0.1b1.dist-info/DESCRIPTION.rst
discord_ext_colours-0.0.1b1.dist-info/METADATA
discord_ext_colours-0.0.1b1.dist-info/RECORD
discord_ext_colours-0.0.1b1.dist-info/WHEEL
discord_ext_colours-0.0.1b1.dist-info/metadata.json
discord_ext_colours-0.0.1b1.dist-info/top_level.txt
